polyhash.py
python_polyhash-0.5.0.dist-info/LICENSE
python_polyhash-0.5.0.dist-info/METADATA
python_polyhash-0.5.0.dist-info/WHEEL
python_polyhash-0.5.0.dist-info/top_level.txt
python_polyhash-0.5.0.dist-info/RECORD
